arcor2_fit_demo/VERSION
arcor2_fit_demo/__init__.py
arcor2_fit_demo/py.typed
arcor2_fit_demo/data/conveyor_belt.fbx
arcor2_fit_demo/data/kinect_azure.dae
arcor2_fit_demo/data/dobot-m1/dobot_m1.urdf
arcor2_fit_demo/data/dobot-m1/dobot_m1_description/meshes/dobot_m1_axis-2.dae
arcor2_fit_demo/data/dobot-m1/dobot_m1_description/meshes/dobot_m1_axis-3.dae
arcor2_fit_demo/data/dobot-m1/dobot_m1_description/meshes/dobot_m1_axis-4.dae
arcor2_fit_demo/data/dobot-m1/dobot_m1_description/meshes/dobot_m1_base.dae
arcor2_fit_demo/data/dobot-m1/dobot_m1_description/meshes/dobot_m1_stand.dae
arcor2_fit_demo/data/dobot-m1/dobot_m1_description/meshes/dobot_m1_z-axis.dae
arcor2_fit_demo/data/dobot-magician/dobot_magician.xml
arcor2_fit_demo/data/dobot-magician/dobot/model/meshes/dae/magicianBase.dae
arcor2_fit_demo/data/dobot-magician/dobot/model/meshes/dae/magicianGripper.dae
arcor2_fit_demo/data/dobot-magician/dobot/model/meshes/dae/magicianLink1.dae
arcor2_fit_demo/data/dobot-magician/dobot/model/meshes/dae/magicianLink2.dae
arcor2_fit_demo/data/dobot-magician/dobot/model/meshes/dae/magicianLink3.dae
arcor2_fit_demo/data/dobot-magician/dobot/model/meshes/dae/magicianLink4.dae
arcor2_fit_demo/data/dobot-magician/dobot/model/meshes/dae/magicianSuctionCup.dae
arcor2_fit_demo/object_types/__init__.py
arcor2_fit_demo/object_types/abstract_dobot.py
arcor2_fit_demo/object_types/conveyor_belt.py
arcor2_fit_demo/object_types/dobot_m1.py
arcor2_fit_demo/object_types/dobot_magician.py
arcor2_fit_demo/object_types/erp.py
arcor2_fit_demo/object_types/fit_common_mixin.py
arcor2_fit_demo/object_types/milling_machine.py
arcor2_fit_demo/object_types/optical_quality_control.py
arcor2_fit_demo/scripts/__init__.py
arcor2_fit_demo/scripts/upload_objects.py
arcor2_fit_demo-1.5.0.dist-info/METADATA
arcor2_fit_demo-1.5.0.dist-info/WHEEL
arcor2_fit_demo-1.5.0.dist-info/entry_points.txt
arcor2_fit_demo-1.5.0.dist-info/namespace_packages.txt
arcor2_fit_demo-1.5.0.dist-info/top_level.txt
arcor2_fit_demo-1.5.0.dist-info/RECORD
