Metadata-Version: 2.1
Name: arcor2-fit-demo
Version: 1.5.0
Summary: ARCOR2 FIT Demo
Author: Robo@FIT
Author-email: imaterna@fit.vut.cz
License: LGPL
Classifier: Development Status :: 3 - Alpha
Classifier: Intended Audience :: Developers
Classifier: Topic :: Software Development :: Build Tools
Classifier: License :: OSI Approved :: GNU Lesser General Public License v3 (LGPLv3)
Classifier: Programming Language :: Python :: 3.11
Classifier: Natural Language :: English
Classifier: Topic :: Scientific/Engineering
Requires-Python: ==3.11.*
Requires-Dist: arcor2-kinect-azure-data (~=0.2.0)
Requires-Dist: arcor2 (~=1.3.0)
